excellm/__init__.py
excellm/__main__.py
excellm/config.py
excellm/excel_session.py
excellm/filters.py
excellm/server.py
excellm/validators.py
excellm/core/__init__.py
excellm/core/audit.py
excellm/core/com_engine.py
excellm/core/connection.py
excellm/core/engine.py
excellm/core/errors.py
excellm/core/file_engine.py
excellm/core/utils.py
excellm/inspection/__init__.py
excellm/inspection/explore.py
excellm/inspection/inspect_workbook.py
excellm/inspection/types.py
excellm/inspection/utils.py
excellm/tools/__init__.py
excellm/tools/chart.py
excellm/tools/formatters.py
excellm/tools/history.py
excellm/tools/pivot.py
excellm/tools/range_ops.py
excellm/tools/readers.py
excellm/tools/screen_capture.py
excellm/tools/search.py
excellm/tools/session.py
excellm/tools/sheet_mgmt.py
excellm/tools/table_ops.py
excellm/tools/vba_execution.py
excellm/tools/workbook.py
excellm/tools/writers.py
excellm-1.2.0.dist-info/METADATA
excellm-1.2.0.dist-info/WHEEL
excellm-1.2.0.dist-info/licenses/LICENSE
excellm-1.2.0.dist-info/RECORD
