Metadata-Version: 2.4
Name: excellm
Version: 1.2.0
Summary: ExceLLM - MCP server for Excel live automation with LLM safety guardrails
Project-URL: Homepage, https://github.com/mroshdy91/Excellm
Project-URL: Documentation, https://github.com/mroshdy91/Excellm/blob/main/README.md
Project-URL: Repository, https://github.com/mroshdy91/Excellm
Project-URL: Bug Tracker, https://github.com/mroshdy91/Excellm/issues
Author-email: ExceLLM Team <support@example.com>
License-File: LICENSE
Keywords: automation,com,excel,excellm,llm,mcp,windows
Classifier: Development Status :: 4 - Beta
Classifier: Intended Audience :: Developers
Classifier: Intended Audience :: System Administrators
Classifier: License :: OSI Approved :: MIT License
Classifier: Operating System :: Microsoft :: Windows
Classifier: Programming Language :: Python :: 3
Classifier: Programming Language :: Python :: 3.10
Classifier: Programming Language :: Python :: 3.11
Classifier: Programming Language :: Python :: 3.12
Classifier: Topic :: Office/Business
Classifier: Topic :: Software Development :: Libraries :: Python Modules
Requires-Python: >=3.10
Requires-Dist: mcp[cli]>=1.2.0
Requires-Dist: pydantic>=2.0.0
Requires-Dist: pywin32>=306; sys_platform == 'win32'
Provides-Extra: dev
Requires-Dist: black>=23.0.0; extra == 'dev'
Requires-Dist: mypy>=1.0.0; extra == 'dev'
Requires-Dist: openpyxl>=3.0.0; extra == 'dev'
Requires-Dist: pytest-asyncio>=0.21.0; extra == 'dev'
Requires-Dist: pytest>=7.0.0; extra == 'dev'
Requires-Dist: ruff>=0.1.0; extra == 'dev'
